LICENSE
MANIFEST.in
README.md
requirements.txt
setup.py
linkero/__init__.py
linkero.egg-info/PKG-INFO
linkero.egg-info/SOURCES.txt
linkero.egg-info/dependency_links.txt
linkero.egg-info/requires.txt
linkero.egg-info/top_level.txt
linkero/config/config.json
linkero/core/__init__.py
linkero/core/ascii.py
linkero/core/common.py
linkero/core/linkero.py
linkero/core/gateway/__init__.py
linkero/core/gateway/gevent_service.py
linkero/core/gateway/waitress_service.py
linkero/tools/__init__.py
linkero/tools/passwordHashGenerator.py