Metadata-Version: 1.1
Name: linkero
Version: 0.9.17
Summary: Restful API for external requests
Home-page: https://github.com/ingran/linkero
Author: Rubén de Celis Hernández
Author-email: contact@rdch106.hol.es
License: LGPL v3
Download-URL: https://github.com/ingran/linkero/archive/v0.9.17.tar.gz
Keywords: framework rest-api restful-api web-services
Platform: UNKNOWN
Classifier: Programming Language :: Python
Classifier: Programming Language :: Python :: 2.7
Classifier: Programming Language :: Python :: 3.4
Classifier: Programming Language :: Python :: 3.5
Classifier: Programming Language :: Python :: 3.6
Classifier: Programming Language :: Python :: 3.7
Classifier: Programming Language :: Python :: 3.8
Classifier: Programming Language :: Python :: 3.9
Classifier: Programming Language :: Python :: 3.10
Classifier: Programming Language :: Python :: Implementation :: PyPy
